LICENSE
README.md
setup.py
austen_plots/AustenPlot.py
austen_plots/__init__.py
austen_plots/math_helpers.py
austen_plots/plot_helpers.py
austen_plots.egg-info/PKG-INFO
austen_plots.egg-info/SOURCES.txt
austen_plots.egg-info/dependency_links.txt
austen_plots.egg-info/not-zip-safe
austen_plots.egg-info/requires.txt
austen_plots.egg-info/top_level.txt