Metadata-Version: 2.1
Name: austen-plots
Version: 0.1.0
Summary: Sensitivity analysis for causal inference
Home-page: https://github.com/anishazaveri/austen_plots
Author: Anisha Zaveri
Author-email: anishazaveri@gmail.com
License: MIT
Platform: UNKNOWN
Classifier: License :: OSI Approved :: MIT License
Classifier: Programming Language :: Python :: 3
Classifier: Programming Language :: Python :: 3.8
License-File: LICENSE
